{
  "type": "minecraft:chest",
  "pools": [
    {
      "rolls": 1,
      "entries": [
        {
          "type": "minecraft:item",
          "weight": 3,
          "name": "minecraft:stick",
          "functions": [
            {
              "function": "minecraft:set_count",
              "count": {
                "min": 3,
                "max": 7
              }
            }
          ]
        },
        {
          "type": "minecraft:item",
          "weight": 2,
          "name": "minecraft:spruce_planks",
          "functions": [
            {
              "function": "minecraft:set_count",
              "count": {
                "min": 3,
                "max": 7
              }
            }
          ]
        },
        {
          "type": "minecraft:item",
          "weight": 1,
          "name": "minecraft:spruce_log",
          "functions": [
            {
              "function": "minecraft:set_count",
              "count": {
                "min": 3,
                "max": 7
              }
            }
          ]
        },
        {
          "type": "minecraft:item",
          "weight": 2,
          "name": "minecraft:torch",
          "functions": [
            {
              "function": "minecraft:set_count",
              "count": {
                "min": 3,
                "max": 7
              }
            }
          ]
        }
      ]
    }
  ],
  "random_sequence": "dungeonnowloading:chests/labyrinth/woods"
}
